setup.cfg
setup.py
shellvars.py
shellvars_py.egg-info/PKG-INFO
shellvars_py.egg-info/SOURCES.txt
shellvars_py.egg-info/dependency_links.txt
shellvars_py.egg-info/top_level.txt