Metadata-Version: 1.1
Name: shellvars-py
Version: 0.1.2
Summary: Read environment variables defined in a shell script into Python.
Home-page: http://github.com/aneilbaboo/shellvars-py
Author: Aneil Mallavarapu
Author-email: aneil.mallavar@gmail.com
License: Apache2
Platform: UNKNOWN
Classifier: Intended Audience :: Developers
Classifier: Natural Language :: English
Classifier: License :: OSI Approved :: Apache Software License
Classifier: Operating System :: MacOS :: MacOS X
Classifier: Programming Language :: Python
Classifier: Programming Language :: Python :: 2
Classifier: Programming Language :: Python :: 2.6
Classifier: Programming Language :: Python :: 2.7
Classifier: Topic :: Software Development :: Libraries :: Python Modules
